<?xml version="1.0" encoding="UTF-8"?>
<?xml-stylesheet type="text/xsl" href="prgs.xsl"?>
<Objects>
   <Charset>UTF-8</Charset>
   <Path>file:///C:/Program Files (x86)/GeneXus/GeneXus18/</Path>
   <Object>
      <ObjCls>0</ObjCls>
      <ObjName>Cidade</ObjName>
      <ObjDesc>Cidade</ObjDesc>
      <ObjLink>/Treinamento2JavaPostgreSQL/com.treinamento2.cidade</ObjLink>
   </Object>
   <Object>
      <ObjCls>0</ObjCls>
      <ObjName>Endereco</ObjName>
      <ObjDesc>Endereco</ObjDesc>
      <ObjLink>/Treinamento2JavaPostgreSQL/com.treinamento2.endereco</ObjLink>
   </Object>
   <Object>
      <ObjCls>0</ObjCls>
      <ObjName>foto_pessoa</ObjName>
      <ObjDesc>foto_pessoa</ObjDesc>
      <ObjLink>/Treinamento2JavaPostgreSQL/com.treinamento2.foto_pessoa</ObjLink>
   </Object>
   <Object>
      <ObjCls>0</ObjCls>
      <ObjName>lotacao</ObjName>
      <ObjDesc>lotacao</ObjDesc>
      <ObjLink>/Treinamento2JavaPostgreSQL/com.treinamento2.lotacao</ObjLink>
   </Object>
   <Object>
      <ObjCls>0</ObjCls>
      <ObjName>Pessoa</ObjName>
      <ObjDesc>Pessoa</ObjDesc>
      <ObjLink>/Treinamento2JavaPostgreSQL/com.treinamento2.pessoa</ObjLink>
   </Object>
   <Object>
      <ObjCls>0</ObjCls>
      <ObjName>servidor_efetivo</ObjName>
      <ObjDesc>servidor_efetivo</ObjDesc>
      <ObjLink>/Treinamento2JavaPostgreSQL/com.treinamento2.servidor_efetivo</ObjLink>
   </Object>
   <Object>
      <ObjCls>0</ObjCls>
      <ObjName>servidor_temporario</ObjName>
      <ObjDesc>servidor_temporario</ObjDesc>
      <ObjLink>/Treinamento2JavaPostgreSQL/com.treinamento2.servidor_temporario</ObjLink>
   </Object>
   <Object>
      <ObjCls>0</ObjCls>
      <ObjName>Unidade</ObjName>
      <ObjDesc>Unidade</ObjDesc>
      <ObjLink>/Treinamento2JavaPostgreSQL/com.treinamento2.unidade</ObjLink>
   </Object>
   <Object>
      <ObjCls>0</ObjCls>
      <ObjName>pessoa_endereco</ObjName>
      <ObjDesc>pessoa_endereco</ObjDesc>
      <ObjLink>/Treinamento2JavaPostgreSQL/com.treinamento2.pessoa_endereco</ObjLink>
   </Object>
   <Object>
      <ObjCls>0</ObjCls>
      <ObjName>unidade_endereco</ObjName>
      <ObjDesc>unidade_endereco</ObjDesc>
      <ObjLink>/Treinamento2JavaPostgreSQL/com.treinamento2.unidade_endereco</ObjLink>
   </Object>
   <Object>
      <ObjCls>0</ObjCls>
      <ObjName>ServLotado</ObjName>
      <ObjDesc>Serv Lotado</ObjDesc>
      <ObjLink>/Treinamento2JavaPostgreSQL/com.treinamento2.servlotado</ObjLink>
   </Object>
   <Object>
      <ObjCls>0</ObjCls>
      <ObjName>End_Funcional</ObjName>
      <ObjDesc>End_Funcional</ObjDesc>
      <ObjLink>/Treinamento2JavaPostgreSQL/com.treinamento2.end_funcional</ObjLink>
   </Object>
</Objects>
